RI_Corrector/RI_Corrector.py
RI_Corrector/__init__.py
RI_Corrector-1.1.dist-info/METADATA
RI_Corrector-1.1.dist-info/WHEEL
RI_Corrector-1.1.dist-info/top_level.txt
RI_Corrector-1.1.dist-info/RECORD
