Metadata-Version: 2.1
Name: RI-Corrector
Version: 1.1
Summary: A tool base on RI to correct RT
Author: Lacter
Author-email: <740318407@qq.com>
Keywords: LC-MS,RI system,RT Correct,Raw LC-MS Data
Classifier: Programming Language :: Python :: 3
Classifier: Operating System :: MacOS :: MacOS X
Classifier: Operating System :: Microsoft :: Windows
Requires-Dist: pyopenms
Requires-Dist: pandas
Requires-Dist: progress
Requires-Dist: matplotlib
Requires-Dist: numpy
